watchful/__about__.py
watchful/__init__.py
watchful/attributes.py
watchful/client.py
watchful/client2.py
watchful/enrich.py
watchful/enricher.py
watchful/types.py
watchful-3.7.0.dist-info/METADATA
watchful-3.7.0.dist-info/WHEEL
watchful-3.7.0.dist-info/licenses/LICENSE
watchful-3.7.0.dist-info/RECORD
