Metadata-Version: 2.1
Name: watchful
Version: 3.7.0
Summary: Watchful API for Interacting with Watchful Environment
Project-URL: Bug Tracker, https://github.com/Watchfulio/watchful-py/issues
Project-URL: Homepage, https://github.com/Watchfulio/watchful-py
Author: Inc.
Author-email: Watchful <engineering@watchful.io>
License-Expression: MIT
License-File: LICENSE
Keywords: watchful
Classifier: License :: OSI Approved :: MIT License
Classifier: Operating System :: OS Independent
Classifier: Programming Language :: Python :: 3
Requires-Python: >=3.8
Requires-Dist: chardet>=5.1.0
Requires-Dist: psutil>=5.9.2
Requires-Dist: requests>=2.23.0
Provides-Extra: enrich
Requires-Dist: flair>=0.11.3; extra == 'enrich'
Requires-Dist: spacy>=3.4.1; extra == 'enrich'
Requires-Dist: spacytextblob>=4.0.0; extra == 'enrich'
